DebugInfo/DebugInfo.py
DebugInfo/__init__.py
debuginfo-66.1.0.dist-info/licenses/LICENSE
debuginfo-66.1.0.dist-info/METADATA
debuginfo-66.1.0.dist-info/WHEEL
debuginfo-66.1.0.dist-info/top_level.txt
debuginfo-66.1.0.dist-info/RECORD
