Metadata-Version: 2.4
Name: DebugInfo
Version: 66.1.0
Summary: 封装提供了一些调试常用方法，例如打印对齐，彩色文本，表格输出，交互接口，秒表装饰器，入参基类等类和方法的封装
Author-email: douyaoyuan <douyaoyuan@126.com>
Project-URL: Homepage, https://gitee.com/DyyYq/DebugInfo.git
Project-URL: Bug Tracker, https://gitee.com/DyyYq/DebugInfo/issues
Classifier: Programming Language :: Python :: 3
Classifier: License :: OSI Approved :: GNU General Public License (GPL)
Classifier: Operating System :: OS Independent
Requires-Python: >=3.9
License-File: LICENSE
Requires-Dist: argparse>=1.4.0
Requires-Dist: chardet>=5.2.0
Requires-Dist: colorama>=0.4.6
Requires-Dist: paramiko>=3.5.0
Requires-Dist: pyperclip>=1.9.0
Requires-Dist: requests>=2.32.3
Requires-Dist: wcwidth>=0.2.13
Dynamic: license-file
